<?xml version="1.0" encoding="UTF-8"?>
<!--
=============================================================================================
Dit bestand bevat een XML serialisatie van een informatiemodel dat is gemodelleerd volgens de 
"Metamodel Informatie Modellering (MIM)" standaard versie 1.2.
Zie: https://docs.geostandaarden.nl/mim/mim/ voor de laatste versie van de standaard.

In deze serialisatie komen <mim-ref:xRef> elementen voor, zoals <mim-ref:ObjecttypeRef>. 
Deze elementen zijn verwijzingen naar een type modelelement X elders in deze serialisatie. 
Via xlink:href attribuut wordt naar betreffende ID verwezen, voorafgegaan door een # teken.
Ook kan men de naam van het modelelement zelf gebruiken, zoals deze in de inhoud van het 
element is opgenomen.

Waar mogelijk is een referentie naar de officiele uitleg (met name de MIM standaard) als 
commentaar toegevoegd. Dat is alleen bij de éérste opkomst van een contructie gedaan.
=============================================================================================
-->
<mim:Informatiemodel xmlns:cs="http://www.imvertor.org/metamodels/conceptualschemas/model/v20181210"
                     xmlns:dlogger="http://www.armatiek.nl/functions/dlogger-proxy"
                     xmlns:mim="http://www.geostandaarden.nl/mim/mim-core/1.2"
                     xmlns:mim-ext="http://www.geostandaarden.nl/mim/mim-ext/1.0"
                     xmlns:mim-ref="http://www.geostandaarden.nl/mim/mim-ref/1.0"
                     xmlns:xhtml="http://www.w3.org/1999/xhtml"
                     xmlns:xlink="http://www.w3.org/1999/xlink"
                     xmlns:xs="http://www.w3.org/2001/XMLSchema"
                     xmlns:xsi="http://www.w3.org/2001/XMLSchema-instance"
                     xsi:schemaLocation="http://www.geostandaarden.nl/mim/mim-core/1.2 xsd/1.2/MIMFORMAT_Mim_relatiesoort.xsd"
                     id="imcartografie-d11965e2"><!--https://docs.geostandaarden.nl/mim/mim/#metagegeven-naam-->
   <mim:naam>IMCartografie</mim:naam>
   <!--https://docs.geostandaarden.nl/mim/mim/#metagegeven-herkomst-->
   <mim:herkomst>Kadaster</mim:herkomst>
   <!--https://docs.geostandaarden.nl/mim/mim/#metagegeven-definitie-->
   <mim:definitie>
      <xhtml:body>
         <xhtml:p>Dit beschrijft het datamodel van de kleinschalige BRT-producten: TOP25NL, TOP50NL, TOP100NL, TOP250NL, TOP500NL, TOP1000NL en de BRT-Achtergrondkaart.
Deze producten hebben eenzelfde model, maar wel een eigen detailniveau.</xhtml:p>
      </xhtml:body>
   </mim:definitie>
   <!--https://docs.geostandaarden.nl/mim/mim/#metagegeven-herkomst-definitie-->
   <mim:herkomstDefinitie><!-- FOUT: De waarde voor dit verplichte metagegeven is niet gespecificeerd in het model --></mim:herkomstDefinitie>
   <!--https://docs.geostandaarden.nl/mim/mim/#metagegeven-datum-opname-->
   <mim:datumOpname><!-- FOUT: De waarde voor dit verplichte metagegeven is niet gespecificeerd in het model --></mim:datumOpname>
   <!--https://docs.geostandaarden.nl/mim/mim/#metagegeven-informatiemodel-type-->
   <mim:informatiemodeltype>Logisch</mim:informatiemodeltype>
   <!--https://docs.geostandaarden.nl/mim/mim/#metagegeven-informatiedomein-->
   <mim:informatiedomein>cartografie</mim:informatiedomein>
   <!--https://docs.geostandaarden.nl/mim/mim/#metagegeven-relatiemodelleringstype-->
   <mim:relatiemodelleringstype>Relatiesoort leidend</mim:relatiemodelleringstype>
   <!--https://docs.geostandaarden.nl/mim/mim/#metagegeven-mim-versie-->
   <mim:MIMVersie>1.2</mim:MIMVersie>
   <mim:packages><!--https://docs.geostandaarden.nl/mim/mim/#domein-->
      <mim:Domein index="124" id="imcartografie-cartografie-d11965e28">
         <mim:naam>Cartografie</mim:naam>
         <mim:herkomst>Kadaster</mim:herkomst>
         <mim:definitie><!-- FOUT: De waarde voor dit verplichte metagegeven is niet gespecificeerd in het model --></mim:definitie>
         <mim:herkomstDefinitie>BRT</mim:herkomstDefinitie>
         <mim:datumOpname>10-04-2025</mim:datumOpname>
         <mim:objecttypen><!--https://docs.geostandaarden.nl/mim/mim/#objecttype-->
            <mim:Objecttype index="151"
                            id="imcartografie-cartografie-cartografischobject-d11965e40">
               <mim:naam>CartografischObject</mim:naam>
               <!--https://docs.geostandaarden.nl/mim/mim/#metagegeven-alias-->
               <mim:alias>Cartografisch object</mim:alias>
               <mim:herkomst>BRT</mim:herkomst>
               <mim:definitie>
                  <xhtml:body>
                     <xhtml:p>Een cartografisch object is een object op een kaart.</xhtml:p>
                  </xhtml:body>
               </mim:definitie>
               <mim:herkomstDefinitie>BRT</mim:herkomstDefinitie>
               <!--https://docs.geostandaarden.nl/mim/mim/#metagegeven-toelichting-->
               <mim:toelichting>Een cartografisch object is bijvoorbeeld een symbool, tekst, lijn of vlak die te onderscheiden is op een kaart.</mim:toelichting>
               <mim:datumOpname>10-04-2025</mim:datumOpname>
               <!--https://docs.geostandaarden.nl/mim/mim/#metagegeven-indicatie-abstract-object-->
               <mim:indicatieAbstractObject>true</mim:indicatieAbstractObject>
               <mim:attribuutsoorten><!--https://docs.geostandaarden.nl/mim/mim/#attribuutsoort-->
                  <mim:Attribuutsoort index="168"
                                      id="imcartografie-cartografie-cartografischobject-objecttype-d11965e64">
                     <mim:naam>objecttype</mim:naam>
                     <mim:herkomst><!-- FOUT: De waarde voor dit verplichte metagegeven is niet gespecificeerd in het model --></mim:herkomst>
                     <mim:definitie>
                        <xhtml:body>
                           <xhtml:p>Aanduiding uit welke BRT-objecttype het cartografisch object hoofdzakelijk afgeleid is.</xhtml:p>
                        </xhtml:body>
                     </mim:definitie>
                     <mim:herkomstDefinitie><!-- FOUT: De waarde voor dit verplichte metagegeven is niet gespecificeerd in het model --></mim:herkomstDefinitie>
                     <mim:datumOpname><!-- FOUT: De waarde voor dit verplichte metagegeven is niet gespecificeerd in het model --></mim:datumOpname>
                     <!--https://docs.geostandaarden.nl/mim/mim/#metagegeven-type-domein-van-een-waarde-een-gegeven-->
                     <mim:type>
                        <mim:Datatype index="168">CharacterString</mim:Datatype>
                     </mim:type>
                     <!--https://docs.geostandaarden.nl/mim/mim/#metagegeven-indicatie-materiele-historie-->
                     <mim:indicatieMaterieleHistorie>false</mim:indicatieMaterieleHistorie>
                     <!--https://docs.geostandaarden.nl/mim/mim/#metagegeven-indicatie-formele-historie-->
                     <mim:indicatieFormeleHistorie>false</mim:indicatieFormeleHistorie>
                     <!--https://docs.geostandaarden.nl/mim/mim/#metagegeven-kardinaliteit-->
                     <mim:kardinaliteit>1</mim:kardinaliteit>
                     <!--https://docs.geostandaarden.nl/mim/mim/#metagegeven-authentiek-->
                     <mim:authentiek>Authentiek</mim:authentiek>
                     <!--https://docs.geostandaarden.nl/mim/mim/#metagegeven-indicatie-afleidbaar-->
                     <mim:indicatieAfleidbaar>false</mim:indicatieAfleidbaar>
                     <!--https://docs.geostandaarden.nl/mim/mim/#metagegeven-indicatie-classificerend-->
                     <mim:indicatieClassificerend>false</mim:indicatieClassificerend>
                     <!--https://docs.geostandaarden.nl/mim/mim/#metagegeven-mogelijk-geen-waarde-->
                     <mim:mogelijkGeenWaarde>false</mim:mogelijkGeenWaarde>
                     <!--https://docs.geostandaarden.nl/mim/mim/#metagegeven-identificerend-->
                     <mim:identificerend>false</mim:identificerend>
                     <mim-ext:kenmerken>
                        <mim-ext:Kenmerk naam="Is afgeleid">Zie package</mim-ext:Kenmerk>
                        <mim-ext:Kenmerk naam="Reden geen waarde">Nee</mim-ext:Kenmerk>
                        <mim-ext:Kenmerk naam="positie">100</mim-ext:Kenmerk>
                     </mim-ext:kenmerken>
                  </mim:Attribuutsoort>
                  <mim:Attribuutsoort index="218"
                                      id="imcartografie-cartografie-cartografischobject-tijdstipregistratie-d11965e108">
                     <mim:naam>tijdstipRegistratie</mim:naam>
                     <mim:herkomst><!-- FOUT: De waarde voor dit verplichte metagegeven is niet gespecificeerd in het model --></mim:herkomst>
                     <mim:definitie>
                        <xhtml:body>
                           <xhtml:p>Tijdstip waarop deze versie van het cartografisch object is afgeleid.</xhtml:p>
                        </xhtml:body>
                     </mim:definitie>
                     <mim:herkomstDefinitie><!-- FOUT: De waarde voor dit verplichte metagegeven is niet gespecificeerd in het model --></mim:herkomstDefinitie>
                     <mim:toelichting>Dit is het tijdstip van het assembleren van het product.</mim:toelichting>
                     <mim:datumOpname>10-04-2025</mim:datumOpname>
                     <mim:type>
                        <mim:Datatype index="218">Date</mim:Datatype>
                     </mim:type>
                     <mim:indicatieMaterieleHistorie>false</mim:indicatieMaterieleHistorie>
                     <mim:indicatieFormeleHistorie>false</mim:indicatieFormeleHistorie>
                     <mim:kardinaliteit>1</mim:kardinaliteit>
                     <mim:authentiek><!-- FOUT: De waarde voor dit verplichte metagegeven is niet gespecificeerd in het model --></mim:authentiek>
                     <mim:indicatieAfleidbaar>false</mim:indicatieAfleidbaar>
                     <mim:indicatieClassificerend>false</mim:indicatieClassificerend>
                     <mim:mogelijkGeenWaarde>false</mim:mogelijkGeenWaarde>
                     <mim:identificerend>false</mim:identificerend>
                     <mim-ext:kenmerken>
                        <mim-ext:Kenmerk naam="positie">100</mim-ext:Kenmerk>
                     </mim-ext:kenmerken>
                  </mim:Attribuutsoort>
                  <mim:Attribuutsoort index="265"
                                      id="imcartografie-cartografie-cartografischobject-visualisatiecode-d11965e150">
                     <mim:naam>visualisatiecode</mim:naam>
                     <mim:herkomst><!-- FOUT: De waarde voor dit verplichte metagegeven is niet gespecificeerd in het model --></mim:herkomst>
                     <mim:definitie>
                        <xhtml:body>
                           <xhtml:p>Code voor het visualiseren van het object.</xhtml:p>
                        </xhtml:body>
                     </mim:definitie>
                     <mim:herkomstDefinitie><!-- FOUT: De waarde voor dit verplichte metagegeven is niet gespecificeerd in het model --></mim:herkomstDefinitie>
                     <mim:datumOpname>10-04-2025</mim:datumOpname>
                     <mim:type>
                        <mim:Datatype index="265">CharacterString</mim:Datatype>
                     </mim:type>
                     <mim:indicatieMaterieleHistorie>false</mim:indicatieMaterieleHistorie>
                     <mim:indicatieFormeleHistorie>false</mim:indicatieFormeleHistorie>
                     <mim:kardinaliteit>1</mim:kardinaliteit>
                     <mim:authentiek><!-- FOUT: De waarde voor dit verplichte metagegeven is niet gespecificeerd in het model --></mim:authentiek>
                     <mim:indicatieAfleidbaar>false</mim:indicatieAfleidbaar>
                     <mim:indicatieClassificerend>false</mim:indicatieClassificerend>
                     <mim:mogelijkGeenWaarde>false</mim:mogelijkGeenWaarde>
                     <mim:identificerend>false</mim:identificerend>
                     <mim-ext:kenmerken>
                        <mim-ext:Kenmerk naam="positie">100</mim-ext:Kenmerk>
                     </mim-ext:kenmerken>
                  </mim:Attribuutsoort>
                  <mim:Attribuutsoort index="309"
                                      id="imcartografie-cartografie-cartografischobject-beschrijving-d11965e190">
                     <mim:naam>beschrijving</mim:naam>
                     <mim:herkomst><!-- FOUT: De waarde voor dit verplichte metagegeven is niet gespecificeerd in het model --></mim:herkomst>
                     <mim:definitie>
                        <xhtml:body>
                           <xhtml:p>Tekstuele uitleg van de visualisatiecode.</xhtml:p>
                        </xhtml:body>
                     </mim:definitie>
                     <mim:herkomstDefinitie><!-- FOUT: De waarde voor dit verplichte metagegeven is niet gespecificeerd in het model --></mim:herkomstDefinitie>
                     <mim:datumOpname>10-04-2025</mim:datumOpname>
                     <mim:type>
                        <mim:Datatype index="309">CharacterString</mim:Datatype>
                     </mim:type>
                     <mim:indicatieMaterieleHistorie>false</mim:indicatieMaterieleHistorie>
                     <mim:indicatieFormeleHistorie>false</mim:indicatieFormeleHistorie>
                     <mim:kardinaliteit>1</mim:kardinaliteit>
                     <mim:authentiek><!-- FOUT: De waarde voor dit verplichte metagegeven is niet gespecificeerd in het model --></mim:authentiek>
                     <mim:indicatieAfleidbaar>false</mim:indicatieAfleidbaar>
                     <mim:indicatieClassificerend>false</mim:indicatieClassificerend>
                     <mim:mogelijkGeenWaarde>false</mim:mogelijkGeenWaarde>
                     <mim:identificerend>false</mim:identificerend>
                     <mim-ext:kenmerken>
                        <mim-ext:Kenmerk naam="positie">100</mim-ext:Kenmerk>
                     </mim-ext:kenmerken>
                  </mim:Attribuutsoort>
                  <mim:Attribuutsoort index="353"
                                      id="imcartografie-cartografie-cartografischobject-symboolurl-d11965e230">
                     <mim:naam>symboolUrl</mim:naam>
                     <mim:herkomst><!-- FOUT: De waarde voor dit verplichte metagegeven is niet gespecificeerd in het model --></mim:herkomst>
                     <mim:definitie>
                        <xhtml:body>
                           <xhtml:p>Verwijzing naar de online plek waar de afbeelding van het symbool geplaatst is.</xhtml:p>
                        </xhtml:body>
                     </mim:definitie>
                     <mim:herkomstDefinitie><!-- FOUT: De waarde voor dit verplichte metagegeven is niet gespecificeerd in het model --></mim:herkomstDefinitie>
                     <mim:datumOpname>10-04-2025</mim:datumOpname>
                     <mim:type>
                        <mim:Datatype index="353">URI</mim:Datatype>
                     </mim:type>
                     <mim:indicatieMaterieleHistorie>false</mim:indicatieMaterieleHistorie>
                     <mim:indicatieFormeleHistorie>false</mim:indicatieFormeleHistorie>
                     <mim:kardinaliteit>0..1</mim:kardinaliteit>
                     <mim:authentiek><!-- FOUT: De waarde voor dit verplichte metagegeven is niet gespecificeerd in het model --></mim:authentiek>
                     <mim:indicatieAfleidbaar>false</mim:indicatieAfleidbaar>
                     <mim:indicatieClassificerend>false</mim:indicatieClassificerend>
                     <mim:mogelijkGeenWaarde>false</mim:mogelijkGeenWaarde>
                     <mim:identificerend>false</mim:identificerend>
                     <mim-ext:kenmerken>
                        <mim-ext:Kenmerk naam="positie">100</mim-ext:Kenmerk>
                     </mim-ext:kenmerken>
                  </mim:Attribuutsoort>
               </mim:attribuutsoorten>
               <mim-ext:kenmerken>
                  <mim-ext:Kenmerk naam="version">1.0</mim-ext:Kenmerk>
               </mim-ext:kenmerken>
            </mim:Objecttype>
            <mim:Objecttype index="420" id="imcartografie-cartografie-kaarttekst-d11965e273">
               <mim:naam>Kaarttekst</mim:naam>
               <mim:herkomst>BRT</mim:herkomst>
               <mim:definitie>
                  <xhtml:body>
                     <xhtml:p>Cartografisch data-product van de teksten op de kaart.</xhtml:p>
                  </xhtml:body>
               </mim:definitie>
               <mim:herkomstDefinitie>BRT</mim:herkomstDefinitie>
               <mim:toelichting>Dit zijn de teksten op de kaart.</mim:toelichting>
               <mim:datumOpname>10-04-2025</mim:datumOpname>
               <mim:indicatieAbstractObject>false</mim:indicatieAbstractObject>
               <mim:supertypen>
                  <mim:GeneralisatieObjecttypen index="436" id="imcartografie-cartografie-kaarttekst-d11965e295">
                     <mim:datumOpname><!-- FOUT: De waarde voor dit verplichte metagegeven is niet gespecificeerd in het model --></mim:datumOpname>
                     <!--https://docs.geostandaarden.nl/mim/vv-st-mim-20240408/#metagegeven-mixin-->
                     <mim:mixin>false</mim:mixin>
                     <mim:supertype>
                        <mim-ref:ObjecttypeRef index="436"
                                               xlink:href="#imcartografie-cartografie-cartografischobject-d11965e40">CartografischObject</mim-ref:ObjecttypeRef>
                     </mim:supertype>
                     <mim-ext:kenmerken>
                        <mim-ext:Kenmerk naam="positie">100</mim-ext:Kenmerk>
                        <mim-ext:Kenmerk naam="type">GENERALISATIE</mim-ext:Kenmerk>
                     </mim-ext:kenmerken>
                  </mim:GeneralisatieObjecttypen>
               </mim:supertypen>
               <mim:attribuutsoorten>
                  <mim:Attribuutsoort index="444"
                                      id="imcartografie-cartografie-kaarttekst-geometrie-d11965e309">
                     <mim:naam>geometrie</mim:naam>
                     <mim:herkomst>BRT</mim:herkomst>
                     <mim:definitie>
                        <xhtml:body>
                           <xhtml:p>De geometrie van het object.</xhtml:p>
                        </xhtml:body>
                     </mim:definitie>
                     <mim:herkomstDefinitie>BRT</mim:herkomstDefinitie>
                     <mim:toelichting>De geometrie is een punt of lijn.</mim:toelichting>
                     <mim:datumOpname>10-04-2025</mim:datumOpname>
                     <mim:type>
                        <mim-ref:KeuzeRef index="444"
                                          xlink:href="#imcartografie-cartografie-lijnofpunt-d11965e842">LijnOfPunt</mim-ref:KeuzeRef>
                     </mim:type>
                     <mim:indicatieMaterieleHistorie>false</mim:indicatieMaterieleHistorie>
                     <mim:indicatieFormeleHistorie>false</mim:indicatieFormeleHistorie>
                     <mim:kardinaliteit>1</mim:kardinaliteit>
                     <mim:authentiek><!-- FOUT: De waarde voor dit verplichte metagegeven is niet gespecificeerd in het model --></mim:authentiek>
                     <mim:indicatieAfleidbaar>false</mim:indicatieAfleidbaar>
                     <mim:indicatieClassificerend>false</mim:indicatieClassificerend>
                     <mim:mogelijkGeenWaarde>false</mim:mogelijkGeenWaarde>
                     <mim:identificerend>false</mim:identificerend>
                     <mim-ext:kenmerken>
                        <mim-ext:Kenmerk naam="positie">100</mim-ext:Kenmerk>
                     </mim-ext:kenmerken>
                  </mim:Attribuutsoort>
                  <mim:Attribuutsoort index="491"
                                      id="imcartografie-cartografie-kaarttekst-tekstsoort-d11965e351">
                     <mim:naam>tekstsoort</mim:naam>
                     <mim:herkomst><!-- FOUT: De waarde voor dit verplichte metagegeven is niet gespecificeerd in het model --></mim:herkomst>
                     <mim:definitie>
                        <xhtml:body>
                           <xhtml:p>Aanduiding uit welk attribuut de kaarttekst afkomstig is.</xhtml:p>
                        </xhtml:body>
                     </mim:definitie>
                     <mim:herkomstDefinitie><!-- FOUT: De waarde voor dit verplichte metagegeven is niet gespecificeerd in het model --></mim:herkomstDefinitie>
                     <mim:toelichting>Dit geeft aan dat de tekst bijvoorbeeld een naam, soortnaam, wegnummer, afritnummer, afritnaam, knooppuntnaam, brugnaam, tunnelnaam, sluisnaam, nummer, hoogte, ... is.</mim:toelichting>
                     <mim:datumOpname>10-04-2025</mim:datumOpname>
                     <mim:type>
                        <mim:Datatype index="491">CharacterString</mim:Datatype>
                     </mim:type>
                     <mim:indicatieMaterieleHistorie>false</mim:indicatieMaterieleHistorie>
                     <mim:indicatieFormeleHistorie>false</mim:indicatieFormeleHistorie>
                     <mim:kardinaliteit>1</mim:kardinaliteit>
                     <mim:authentiek><!-- FOUT: De waarde voor dit verplichte metagegeven is niet gespecificeerd in het model --></mim:authentiek>
                     <mim:indicatieAfleidbaar>false</mim:indicatieAfleidbaar>
                     <mim:indicatieClassificerend>false</mim:indicatieClassificerend>
                     <mim:mogelijkGeenWaarde>false</mim:mogelijkGeenWaarde>
                     <mim:identificerend>false</mim:identificerend>
                     <mim-ext:kenmerken>
                        <mim-ext:Kenmerk naam="positie">100</mim-ext:Kenmerk>
                     </mim-ext:kenmerken>
                  </mim:Attribuutsoort>
                  <mim:Attribuutsoort index="538" id="imcartografie-cartografie-kaarttekst-tekst-d11965e393">
                     <mim:naam>tekst</mim:naam>
                     <mim:herkomst><!-- FOUT: De waarde voor dit verplichte metagegeven is niet gespecificeerd in het model --></mim:herkomst>
                     <mim:definitie>
                        <xhtml:body>
                           <xhtml:p>De tekst die op de kaart weergegeven wordt.</xhtml:p>
                        </xhtml:body>
                     </mim:definitie>
                     <mim:herkomstDefinitie><!-- FOUT: De waarde voor dit verplichte metagegeven is niet gespecificeerd in het model --></mim:herkomstDefinitie>
                     <mim:datumOpname>10-04-2025</mim:datumOpname>
                     <mim:type>
                        <mim:Datatype index="538">CharacterString</mim:Datatype>
                     </mim:type>
                     <mim:indicatieMaterieleHistorie>false</mim:indicatieMaterieleHistorie>
                     <mim:indicatieFormeleHistorie>false</mim:indicatieFormeleHistorie>
                     <mim:kardinaliteit>1</mim:kardinaliteit>
                     <mim:authentiek><!-- FOUT: De waarde voor dit verplichte metagegeven is niet gespecificeerd in het model --></mim:authentiek>
                     <mim:indicatieAfleidbaar>false</mim:indicatieAfleidbaar>
                     <mim:indicatieClassificerend>false</mim:indicatieClassificerend>
                     <mim:mogelijkGeenWaarde>false</mim:mogelijkGeenWaarde>
                     <mim:identificerend>false</mim:identificerend>
                     <mim-ext:kenmerken>
                        <mim-ext:Kenmerk naam="positie">100</mim-ext:Kenmerk>
                     </mim-ext:kenmerken>
                  </mim:Attribuutsoort>
                  <mim:Attribuutsoort index="582" id="imcartografie-cartografie-kaarttekst-klasse-d11965e433">
                     <mim:naam>klasse</mim:naam>
                     <mim:herkomst><!-- FOUT: De waarde voor dit verplichte metagegeven is niet gespecificeerd in het model --></mim:herkomst>
                     <mim:definitie>
                        <xhtml:body>
                           <xhtml:p>Indeling die gebruikt wordt voor het bepalen van de eigenschappen van de kaarttekst.</xhtml:p>
                        </xhtml:body>
                     </mim:definitie>
                     <mim:herkomstDefinitie><!-- FOUT: De waarde voor dit verplichte metagegeven is niet gespecificeerd in het model --></mim:herkomstDefinitie>
                     <mim:toelichting>Bijvoorbeeld de grootte of het gebruikte font.</mim:toelichting>
                     <mim:datumOpname>10-04-2025</mim:datumOpname>
                     <mim:type>
                        <mim:Datatype index="582">CharacterString</mim:Datatype>
                     </mim:type>
                     <mim:indicatieMaterieleHistorie>false</mim:indicatieMaterieleHistorie>
                     <mim:indicatieFormeleHistorie>false</mim:indicatieFormeleHistorie>
                     <mim:kardinaliteit>1</mim:kardinaliteit>
                     <mim:authentiek><!-- FOUT: De waarde voor dit verplichte metagegeven is niet gespecificeerd in het model --></mim:authentiek>
                     <mim:indicatieAfleidbaar>false</mim:indicatieAfleidbaar>
                     <mim:indicatieClassificerend>false</mim:indicatieClassificerend>
                     <mim:mogelijkGeenWaarde>false</mim:mogelijkGeenWaarde>
                     <mim:identificerend>false</mim:identificerend>
                     <mim-ext:kenmerken>
                        <mim-ext:Kenmerk naam="positie">100</mim-ext:Kenmerk>
                     </mim-ext:kenmerken>
                  </mim:Attribuutsoort>
                  <mim:Attribuutsoort index="629"
                                      id="imcartografie-cartografie-kaarttekst-prioriteit-d11965e475">
                     <mim:naam>prioriteit</mim:naam>
                     <mim:herkomst><!-- FOUT: De waarde voor dit verplichte metagegeven is niet gespecificeerd in het model --></mim:herkomst>
                     <mim:definitie>
                        <xhtml:body>
                           <xhtml:p>Indeling die gebruikt wordt voor het bepalen van de belangrijkheid van de kaarttekst.</xhtml:p>
                        </xhtml:body>
                     </mim:definitie>
                     <mim:herkomstDefinitie><!-- FOUT: De waarde voor dit verplichte metagegeven is niet gespecificeerd in het model --></mim:herkomstDefinitie>
                     <mim:datumOpname><!-- FOUT: De waarde voor dit verplichte metagegeven is niet gespecificeerd in het model --></mim:datumOpname>
                     <mim:type>
                        <mim:Datatype index="629">CharacterString</mim:Datatype>
                     </mim:type>
                     <mim:indicatieMaterieleHistorie>false</mim:indicatieMaterieleHistorie>
                     <mim:indicatieFormeleHistorie>false</mim:indicatieFormeleHistorie>
                     <mim:kardinaliteit>1</mim:kardinaliteit>
                     <mim:authentiek><!-- FOUT: De waarde voor dit verplichte metagegeven is niet gespecificeerd in het model --></mim:authentiek>
                     <mim:indicatieAfleidbaar>false</mim:indicatieAfleidbaar>
                     <mim:indicatieClassificerend>false</mim:indicatieClassificerend>
                     <mim:mogelijkGeenWaarde>false</mim:mogelijkGeenWaarde>
                     <mim:identificerend>false</mim:identificerend>
                     <mim-ext:kenmerken>
                        <mim-ext:Kenmerk naam="positie">100</mim-ext:Kenmerk>
                     </mim-ext:kenmerken>
                  </mim:Attribuutsoort>
                  <mim:Attribuutsoort index="670"
                                      id="imcartografie-cartografie-kaarttekst-rotatie-d11965e515">
                     <mim:naam>rotatie</mim:naam>
                     <mim:herkomst><!-- FOUT: De waarde voor dit verplichte metagegeven is niet gespecificeerd in het model --></mim:herkomst>
                     <mim:definitie>
                        <xhtml:body>
                           <xhtml:p>Draaiingshoek voor de plaatsing van de kaarttekst.</xhtml:p>
                        </xhtml:body>
                     </mim:definitie>
                     <mim:herkomstDefinitie><!-- FOUT: De waarde voor dit verplichte metagegeven is niet gespecificeerd in het model --></mim:herkomstDefinitie>
                     <mim:datumOpname>10-04-2025</mim:datumOpname>
                     <mim:type>
                        <mim:Datatype index="670">Integer</mim:Datatype>
                     </mim:type>
                     <mim:indicatieMaterieleHistorie>false</mim:indicatieMaterieleHistorie>
                     <mim:indicatieFormeleHistorie>false</mim:indicatieFormeleHistorie>
                     <mim:kardinaliteit>0..1</mim:kardinaliteit>
                     <mim:authentiek><!-- FOUT: De waarde voor dit verplichte metagegeven is niet gespecificeerd in het model --></mim:authentiek>
                     <mim:indicatieAfleidbaar>false</mim:indicatieAfleidbaar>
                     <mim:indicatieClassificerend>false</mim:indicatieClassificerend>
                     <mim:mogelijkGeenWaarde>false</mim:mogelijkGeenWaarde>
                     <mim:identificerend>false</mim:identificerend>
                     <mim-ext:kenmerken>
                        <mim-ext:Kenmerk naam="positie">100</mim-ext:Kenmerk>
                     </mim-ext:kenmerken>
                  </mim:Attribuutsoort>
               </mim:attribuutsoorten>
               <mim-ext:kenmerken>
                  <mim-ext:Kenmerk naam="version">1.0</mim-ext:Kenmerk>
               </mim-ext:kenmerken>
            </mim:Objecttype>
            <mim:Objecttype index="737" id="imcartografie-cartografie-lijnobject-d11965e558">
               <mim:naam>Lijnobject</mim:naam>
               <mim:herkomst>BRT</mim:herkomst>
               <mim:definitie>
                  <xhtml:body>
                     <xhtml:p>Cartografisch data-product van de lijnen op de kaart.</xhtml:p>
                  </xhtml:body>
               </mim:definitie>
               <mim:herkomstDefinitie>BRT</mim:herkomstDefinitie>
               <mim:toelichting>Dit zijn de lijnen op de kaart.</mim:toelichting>
               <mim:datumOpname>10-04-2025</mim:datumOpname>
               <mim:indicatieAbstractObject>false</mim:indicatieAbstractObject>
               <mim:supertypen>
                  <mim:GeneralisatieObjecttypen index="753" id="imcartografie-cartografie-lijnobject-d11965e580">
                     <mim:datumOpname><!-- FOUT: De waarde voor dit verplichte metagegeven is niet gespecificeerd in het model --></mim:datumOpname>
                     <mim:mixin>false</mim:mixin>
                     <mim:supertype>
                        <mim-ref:ObjecttypeRef index="753"
                                               xlink:href="#imcartografie-cartografie-cartografischobject-d11965e40">CartografischObject</mim-ref:ObjecttypeRef>
                     </mim:supertype>
                     <mim-ext:kenmerken>
                        <mim-ext:Kenmerk naam="positie">100</mim-ext:Kenmerk>
                        <mim-ext:Kenmerk naam="type">GENERALISATIE</mim-ext:Kenmerk>
                     </mim-ext:kenmerken>
                  </mim:GeneralisatieObjecttypen>
               </mim:supertypen>
               <mim:attribuutsoorten>
                  <mim:Attribuutsoort index="761"
                                      id="imcartografie-cartografie-lijnobject-geometrie-d11965e594">
                     <mim:naam>geometrie</mim:naam>
                     <mim:herkomst>BRT</mim:herkomst>
                     <mim:definitie>
                        <xhtml:body>
                           <xhtml:p>De geometrie van het object.</xhtml:p>
                        </xhtml:body>
                     </mim:definitie>
                     <mim:herkomstDefinitie>BRT</mim:herkomstDefinitie>
                     <mim:toelichting>De geometrie is een lijn.</mim:toelichting>
                     <mim:datumOpname>10-04-2025</mim:datumOpname>
                     <mim:type>
                        <mim-ext:ConstructieRef index="761" xlink:href="#imcartografie-gmlprofile-gmcurve-d11965e878">GM_Curve</mim-ext:ConstructieRef>
                     </mim:type>
                     <mim:indicatieMaterieleHistorie>false</mim:indicatieMaterieleHistorie>
                     <mim:indicatieFormeleHistorie>false</mim:indicatieFormeleHistorie>
                     <mim:kardinaliteit>1</mim:kardinaliteit>
                     <mim:authentiek><!-- FOUT: De waarde voor dit verplichte metagegeven is niet gespecificeerd in het model --></mim:authentiek>
                     <mim:indicatieAfleidbaar>false</mim:indicatieAfleidbaar>
                     <mim:indicatieClassificerend>false</mim:indicatieClassificerend>
                     <mim:mogelijkGeenWaarde>false</mim:mogelijkGeenWaarde>
                     <mim:identificerend>false</mim:identificerend>
                     <mim-ext:kenmerken>
                        <mim-ext:Kenmerk naam="positie">100</mim-ext:Kenmerk>
                     </mim-ext:kenmerken>
                  </mim:Attribuutsoort>
               </mim:attribuutsoorten>
               <mim-ext:kenmerken>
                  <mim-ext:Kenmerk naam="version">1.0</mim-ext:Kenmerk>
               </mim-ext:kenmerken>
            </mim:Objecttype>
            <mim:Objecttype index="835" id="imcartografie-cartografie-symbool-d11965e639">
               <mim:naam>Symbool</mim:naam>
               <mim:herkomst>BRT</mim:herkomst>
               <mim:definitie>
                  <xhtml:body>
                     <xhtml:p>Cartografisch data-product van punten op de kaart.</xhtml:p>
                  </xhtml:body>
               </mim:definitie>
               <mim:herkomstDefinitie>BRT</mim:herkomstDefinitie>
               <mim:toelichting>Dit zijn de objecten op de kaart die afgebeeld worden als een punt of symbool.</mim:toelichting>
               <mim:datumOpname>10-04-2025</mim:datumOpname>
               <mim:indicatieAbstractObject>false</mim:indicatieAbstractObject>
               <mim:supertypen>
                  <mim:GeneralisatieObjecttypen index="851" id="imcartografie-cartografie-symbool-d11965e661">
                     <mim:datumOpname><!-- FOUT: De waarde voor dit verplichte metagegeven is niet gespecificeerd in het model --></mim:datumOpname>
                     <mim:mixin>false</mim:mixin>
                     <mim:supertype>
                        <mim-ref:ObjecttypeRef index="851"
                                               xlink:href="#imcartografie-cartografie-cartografischobject-d11965e40">CartografischObject</mim-ref:ObjecttypeRef>
                     </mim:supertype>
                     <mim-ext:kenmerken>
                        <mim-ext:Kenmerk naam="positie">100</mim-ext:Kenmerk>
                        <mim-ext:Kenmerk naam="type">GENERALISATIE</mim-ext:Kenmerk>
                     </mim-ext:kenmerken>
                  </mim:GeneralisatieObjecttypen>
               </mim:supertypen>
               <mim:attribuutsoorten>
                  <mim:Attribuutsoort index="859" id="imcartografie-cartografie-symbool-geometrie-d11965e675">
                     <mim:naam>geometrie</mim:naam>
                     <mim:herkomst>BRT</mim:herkomst>
                     <mim:definitie>
                        <xhtml:body>
                           <xhtml:p>De geometrie van het object.</xhtml:p>
                        </xhtml:body>
                     </mim:definitie>
                     <mim:herkomstDefinitie>BRT</mim:herkomstDefinitie>
                     <mim:toelichting>De geometrie is een punt.</mim:toelichting>
                     <mim:datumOpname>10-04-2025</mim:datumOpname>
                     <mim:type>
                        <mim-ext:ConstructieRef index="859" xlink:href="#imcartografie-gmlprofile-gmpoint-d11965e886">GM_Point</mim-ext:ConstructieRef>
                     </mim:type>
                     <mim:indicatieMaterieleHistorie>false</mim:indicatieMaterieleHistorie>
                     <mim:indicatieFormeleHistorie>false</mim:indicatieFormeleHistorie>
                     <mim:kardinaliteit>1</mim:kardinaliteit>
                     <mim:authentiek><!-- FOUT: De waarde voor dit verplichte metagegeven is niet gespecificeerd in het model --></mim:authentiek>
                     <mim:indicatieAfleidbaar>false</mim:indicatieAfleidbaar>
                     <mim:indicatieClassificerend>false</mim:indicatieClassificerend>
                     <mim:mogelijkGeenWaarde>false</mim:mogelijkGeenWaarde>
                     <mim:identificerend>false</mim:identificerend>
                     <mim-ext:kenmerken>
                        <mim-ext:Kenmerk naam="positie">100</mim-ext:Kenmerk>
                     </mim-ext:kenmerken>
                  </mim:Attribuutsoort>
                  <mim:Attribuutsoort index="910" id="imcartografie-cartografie-symbool-rotatie-d11965e717">
                     <mim:naam>rotatie</mim:naam>
                     <mim:herkomst><!-- FOUT: De waarde voor dit verplichte metagegeven is niet gespecificeerd in het model --></mim:herkomst>
                     <mim:definitie>
                        <xhtml:body>
                           <xhtml:p>Draaiingshoek voor de plaatsing van de kaarttekst.</xhtml:p>
                        </xhtml:body>
                     </mim:definitie>
                     <mim:herkomstDefinitie><!-- FOUT: De waarde voor dit verplichte metagegeven is niet gespecificeerd in het model --></mim:herkomstDefinitie>
                     <mim:datumOpname>10-04-2025</mim:datumOpname>
                     <mim:type>
                        <mim:Datatype index="910">Integer</mim:Datatype>
                     </mim:type>
                     <mim:indicatieMaterieleHistorie>false</mim:indicatieMaterieleHistorie>
                     <mim:indicatieFormeleHistorie>false</mim:indicatieFormeleHistorie>
                     <mim:kardinaliteit>0..1</mim:kardinaliteit>
                     <mim:authentiek><!-- FOUT: De waarde voor dit verplichte metagegeven is niet gespecificeerd in het model --></mim:authentiek>
                     <mim:indicatieAfleidbaar>false</mim:indicatieAfleidbaar>
                     <mim:indicatieClassificerend>false</mim:indicatieClassificerend>
                     <mim:mogelijkGeenWaarde>false</mim:mogelijkGeenWaarde>
                     <mim:identificerend>false</mim:identificerend>
                     <mim-ext:kenmerken>
                        <mim-ext:Kenmerk naam="positie">100</mim-ext:Kenmerk>
                     </mim-ext:kenmerken>
                  </mim:Attribuutsoort>
               </mim:attribuutsoorten>
               <mim-ext:kenmerken>
                  <mim-ext:Kenmerk naam="version">1.0</mim-ext:Kenmerk>
               </mim-ext:kenmerken>
            </mim:Objecttype>
            <mim:Objecttype index="977" id="imcartografie-cartografie-vlakobject-d11965e760">
               <mim:naam>Vlakobject</mim:naam>
               <mim:herkomst>BRT</mim:herkomst>
               <mim:definitie>
                  <xhtml:body>
                     <xhtml:p>Cartografisch data-product van de vlakken op de kaart.</xhtml:p>
                  </xhtml:body>
               </mim:definitie>
               <mim:herkomstDefinitie>BRT</mim:herkomstDefinitie>
               <mim:toelichting>Dit zijn de vlakken op de kaart.</mim:toelichting>
               <mim:datumOpname>10-04-2025</mim:datumOpname>
               <mim:indicatieAbstractObject>false</mim:indicatieAbstractObject>
               <mim:supertypen>
                  <mim:GeneralisatieObjecttypen index="993" id="imcartografie-cartografie-vlakobject-d11965e782">
                     <mim:datumOpname><!-- FOUT: De waarde voor dit verplichte metagegeven is niet gespecificeerd in het model --></mim:datumOpname>
                     <mim:mixin>false</mim:mixin>
                     <mim:supertype>
                        <mim-ref:ObjecttypeRef index="993"
                                               xlink:href="#imcartografie-cartografie-cartografischobject-d11965e40">CartografischObject</mim-ref:ObjecttypeRef>
                     </mim:supertype>
                     <mim-ext:kenmerken>
                        <mim-ext:Kenmerk naam="positie">100</mim-ext:Kenmerk>
                        <mim-ext:Kenmerk naam="type">GENERALISATIE</mim-ext:Kenmerk>
                     </mim-ext:kenmerken>
                  </mim:GeneralisatieObjecttypen>
               </mim:supertypen>
               <mim:attribuutsoorten>
                  <mim:Attribuutsoort index="1001"
                                      id="imcartografie-cartografie-vlakobject-geometrie-d11965e796">
                     <mim:naam>geometrie</mim:naam>
                     <mim:herkomst>BRT</mim:herkomst>
                     <mim:definitie>
                        <xhtml:body>
                           <xhtml:p>De geometrie van het object.</xhtml:p>
                        </xhtml:body>
                     </mim:definitie>
                     <mim:herkomstDefinitie>BRT</mim:herkomstDefinitie>
                     <mim:toelichting>De geometrie is een vlak.</mim:toelichting>
                     <mim:datumOpname>10-04-2025</mim:datumOpname>
                     <mim:type>
                        <mim-ext:ConstructieRef index="1001"
                                                xlink:href="#imcartografie-gmlprofile-gmsurface-d11965e894">GM_Surface</mim-ext:ConstructieRef>
                     </mim:type>
                     <mim:indicatieMaterieleHistorie>false</mim:indicatieMaterieleHistorie>
                     <mim:indicatieFormeleHistorie>false</mim:indicatieFormeleHistorie>
                     <mim:kardinaliteit>1</mim:kardinaliteit>
                     <mim:authentiek><!-- FOUT: De waarde voor dit verplichte metagegeven is niet gespecificeerd in het model --></mim:authentiek>
                     <mim:indicatieAfleidbaar>false</mim:indicatieAfleidbaar>
                     <mim:indicatieClassificerend>false</mim:indicatieClassificerend>
                     <mim:mogelijkGeenWaarde>false</mim:mogelijkGeenWaarde>
                     <mim:identificerend>false</mim:identificerend>
                     <mim-ext:kenmerken>
                        <mim-ext:Kenmerk naam="positie">100</mim-ext:Kenmerk>
                     </mim-ext:kenmerken>
                  </mim:Attribuutsoort>
               </mim:attribuutsoorten>
               <mim-ext:kenmerken>
                  <mim-ext:Kenmerk naam="version">1.0</mim-ext:Kenmerk>
               </mim-ext:kenmerken>
            </mim:Objecttype>
         </mim:objecttypen>
         <mim:keuzen>
            <mim:Keuze index="1075" id="imcartografie-cartografie-lijnofpunt-d11965e842">
               <mim:naam>LijnOfPunt</mim:naam>
               <mim:herkomst><!-- FOUT: De waarde voor dit verplichte metagegeven is niet gespecificeerd in het model --></mim:herkomst>
               <mim:datumOpname>10-04-2025</mim:datumOpname>
               <mim:keuzeDatatypen>
                  <mim-ext:ConstructieRef index="1087"
                                          label="lijn"
                                          xlink:href="#imcartografie-gmlprofile-gmcurve-d11965e878">GM_Curve</mim-ext:ConstructieRef>
                  <mim-ext:ConstructieRef index="1115"
                                          label="punt"
                                          xlink:href="#imcartografie-gmlprofile-gmpoint-d11965e886">GM_Point</mim-ext:ConstructieRef>
               </mim:keuzeDatatypen>
               <mim-ext:kenmerken>
                  <mim-ext:Kenmerk naam="version">1.0</mim-ext:Kenmerk>
               </mim-ext:kenmerken>
            </mim:Keuze>
         </mim:keuzen>
         <mim-ext:kenmerken>
            <mim-ext:Kenmerk naam="Release">20251118</mim-ext:Kenmerk>
            <mim-ext:Kenmerk naam="version">1.0</mim-ext:Kenmerk>
            <mim-ext:Kenmerk naam="namespace">http://developer.kadaster.nl/schemas/brt/car/cartografie</mim-ext:Kenmerk>
         </mim-ext:kenmerken>
      </mim:Domein>
      <!--https://docs.geostandaarden.nl/mim/mim/#extern-->
      <mim:Extern index="1229" id="OUTSIDE-2">
         <mim:naam>GMLPROFILE</mim:naam>
         <mim:herkomst>Kadaster</mim:herkomst>
         <mim:definitie>ISO19107 Geographic information – Spatial schema</mim:definitie>
         <mim:herkomstDefinitie><!-- FOUT: De waarde voor dit verplichte metagegeven is niet gespecificeerd in het model --></mim:herkomstDefinitie>
         <mim:datumOpname><!-- FOUT: De waarde voor dit verplichte metagegeven is niet gespecificeerd in het model --></mim:datumOpname>
         <!--https://docs.geostandaarden.nl/mim/mim/#metagegeven-locatie-->
         <mim:locatie>X</mim:locatie>
         <mim-ext:constructies>
            <mim-ext:Constructie index="1264" id="imcartografie-gmlprofile-gmcurve-d11965e878">
               <mim-ext:constructietype>INTERFACE</mim-ext:constructietype>
               <mim:naam>GM_Curve</mim:naam>
               <mim-ext:kenmerken>
                  <mim-ext:Kenmerk naam="oasnaam">linestringGeoJSON</mim-ext:Kenmerk>
               </mim-ext:kenmerken>
            </mim-ext:Constructie>
            <mim-ext:Constructie index="1270" id="imcartografie-gmlprofile-gmpoint-d11965e886">
               <mim-ext:constructietype>INTERFACE</mim-ext:constructietype>
               <mim:naam>GM_Point</mim:naam>
               <mim-ext:kenmerken>
                  <mim-ext:Kenmerk naam="oasnaam">pointGeoJSON</mim-ext:Kenmerk>
               </mim-ext:kenmerken>
            </mim-ext:Constructie>
            <mim-ext:Constructie index="1258" id="imcartografie-gmlprofile-gmsurface-d11965e894">
               <mim-ext:constructietype>INTERFACE</mim-ext:constructietype>
               <mim:naam>GM_Surface</mim:naam>
               <mim-ext:kenmerken>
                  <mim-ext:Kenmerk naam="oasnaam">polygonGeoJSON</mim-ext:Kenmerk>
               </mim-ext:kenmerken>
            </mim-ext:Constructie>
         </mim-ext:constructies>
         <mim-ext:kenmerken>
            <mim-ext:Kenmerk naam="familie">GML</mim-ext:Kenmerk>
            <mim-ext:Kenmerk naam="version">3.2.2</mim-ext:Kenmerk>
            <mim-ext:Kenmerk naam="namespace">http://www.opengis.net/gml/3.2</mim-ext:Kenmerk>
         </mim-ext:kenmerken>
      </mim:Extern>
      <mim:Extern index="1283" id="OUTSIDE-3">
         <mim:naam>GMLSF</mim:naam>
         <mim:herkomst><!-- FOUT: De waarde voor dit verplichte metagegeven is niet gespecificeerd in het model --></mim:herkomst>
         <mim:definitie>GML Simple Feature Profile</mim:definitie>
         <mim:herkomstDefinitie><!-- FOUT: De waarde voor dit verplichte metagegeven is niet gespecificeerd in het model --></mim:herkomstDefinitie>
         <mim:datumOpname><!-- FOUT: De waarde voor dit verplichte metagegeven is niet gespecificeerd in het model --></mim:datumOpname>
         <mim:locatie><!-- FOUT: De waarde voor dit verplichte metagegeven is niet gespecificeerd in het model --></mim:locatie>
         <mim-ext:kenmerken>
            <mim-ext:Kenmerk naam="familie">GML</mim-ext:Kenmerk>
            <mim-ext:Kenmerk naam="version">2.0</mim-ext:Kenmerk>
            <mim-ext:Kenmerk naam="namespace">http://www.opengis.net/gmlsf/2.0</mim-ext:Kenmerk>
         </mim-ext:kenmerken>
      </mim:Extern>
      <mim:Extern index="1172" id="OUTSIDE-1">
         <mim:naam>MIM11</mim:naam>
         <mim:herkomst>MIM</mim:herkomst>
         <mim:definitie>De primitieve datatypen zoals vastgesteld in de MIM 1.1 specificatie</mim:definitie>
         <mim:herkomstDefinitie><!-- FOUT: De waarde voor dit verplichte metagegeven is niet gespecificeerd in het model --></mim:herkomstDefinitie>
         <mim:datumOpname><!-- FOUT: De waarde voor dit verplichte metagegeven is niet gespecificeerd in het model --></mim:datumOpname>
         <mim:locatie>https://docs.geostandaarden.nl/mim/</mim:locatie>
         <mim-ext:constructies>
            <mim-ext:Constructie index="1221" id="imcartografie-mim11-uri-d11965e943">
               <mim-ext:constructietype>INTERFACE</mim-ext:constructietype>
               <mim:naam>URI</mim:naam>
               <mim-ext:kenmerken>
                  <mim-ext:Kenmerk naam="oasnaam">uri</mim-ext:Kenmerk>
               </mim-ext:kenmerken>
            </mim-ext:Constructie>
            <mim-ext:Constructie index="1214" id="imcartografie-mim11-date-d11965e951">
               <mim-ext:constructietype>INTERFACE</mim-ext:constructietype>
               <mim:naam>Date</mim:naam>
               <mim-ext:kenmerken>
                  <mim-ext:Kenmerk naam="oasnaam">date</mim-ext:Kenmerk>
               </mim-ext:kenmerken>
            </mim-ext:Constructie>
            <mim-ext:Constructie index="1207" id="imcartografie-mim11-integer-d11965e959">
               <mim-ext:constructietype>INTERFACE</mim-ext:constructietype>
               <mim:naam>Integer</mim:naam>
               <mim-ext:kenmerken>
                  <mim-ext:Kenmerk naam="oasnaam">integer</mim-ext:Kenmerk>
               </mim-ext:kenmerken>
            </mim-ext:Constructie>
            <mim-ext:Constructie index="1200" id="imcartografie-mim11-characterstring-d11965e967">
               <mim-ext:constructietype>INTERFACE</mim-ext:constructietype>
               <mim:naam>CharacterString</mim:naam>
               <mim-ext:kenmerken>
                  <mim-ext:Kenmerk naam="oasnaam">string</mim-ext:Kenmerk>
               </mim-ext:kenmerken>
            </mim-ext:Constructie>
         </mim-ext:constructies>
         <mim-ext:kenmerken>
            <mim-ext:Kenmerk naam="familie"/>
            <mim-ext:Kenmerk naam="version">1.0.0</mim-ext:Kenmerk>
            <mim-ext:Kenmerk naam="namespace">http://www.geonovum.nl/MIM11</mim-ext:Kenmerk>
         </mim-ext:kenmerken>
      </mim:Extern>
   </mim:packages>
   <mim-ext:kenmerken>
      <mim-ext:Kenmerk naam="Alternatieve naam">TOPNL cartografie</mim-ext:Kenmerk>
      <mim-ext:Kenmerk naam="Imvertor">model</mim-ext:Kenmerk>
      <mim-ext:Kenmerk naam="Is afgeleid">Zie package</mim-ext:Kenmerk>
      <mim-ext:Kenmerk naam="Niveau">specifiek</mim-ext:Kenmerk>
      <mim-ext:Kenmerk naam="Release">20251118</mim-ext:Kenmerk>
      <mim-ext:Kenmerk naam="version">1.0</mim-ext:Kenmerk>
      <mim-ext:Kenmerk naam="namespace">http://developer.kadaster.nl/schemas/brt/car</mim-ext:Kenmerk>
      <mim-ext:Kenmerk naam="imvertor-version">Nightly-build.0</mim-ext:Kenmerk>
   </mim-ext:kenmerken>
</mim:Informatiemodel>
